qleegss/__init__.py
qleegss/handler.py
qleegss/dataload/__init__.py
qleegss/dataload/load_acc.py
qleegss/dataload/load_device_type.py
qleegss/dataload/load_eeg_ar2_one_night.py
qleegss/dataload/load_eeg_ar4_one_night.py
qleegss/dataload/load_eeg_one_epoch.py
qleegss/dataload/load_eeg_x8_one_night copy.py
qleegss/dataload/load_eeg_x8_one_night.py
qleegss/dataload/load_sti.py
qleegss/eeg2edf/DataReader(V1.3).py
qleegss/eeg2edf/__init__.py
qleegss/eeg2edf/data2mat.py
qleegss/eeg2edf/decode_data.py
qleegss/eeg2edf/draw_sleep.py
qleegss/eeg2edf/edf_resample.py
qleegss/eeg2edf/transdata2edf.py
qleegss/eeg2edf/qlelib/IDataFormat.py
qleegss/eeg2edf/qlelib/__init__.py
qleegss/eeg2edf/qlelib/data2edf.py
qleegss/eeg2edf/qlelib/pystruct.py
qleegss/eeg2edf/qlelib/qldata2edf.py
qleegss/eeg2edf/qlelib/qle2edf old.py
qleegss/eeg2edf/qlelib/qle2edf.py
qleegss/eeg2edf/qlelib/qle2edf2.py
qleegss/eeg2edf/qlelib/qle_data_check.py
qleegss/eeg2edf/qlelib/qle_sp_cal.py
qleegss/eeg2edf/qlelib/tdyqle2edf.py
qleegss/eeg2edf/qlelib/tdyqledef.py
qleegss/eeg2edf/qlelib/x7eeg2edf.py
qleegss/eeg2edf/qlelib/x7qledef.py
qleegss/model/__init__.py
qleegss/model/ckpt_fold-01.pth
qleegss/model/predict.py
qleegss/model/predict2.py
qleegss/model/sleepyco_net.py
qleegss/model/wake_acc.py
qleegss/other/__init__.py
qleegss/other/calculate_sleep_score.py
qleegss/other/count_turnover copy.py
qleegss/other/count_turnover.py
qleegss/other/count_turnover2.py
qleegss/other/disconnet_loss_rate.py
qleegss/other/eeg_acc_reshape.py
qleegss/other/metric.py
qleegss/other/save_mat.py
qleegss/pdf/__init__.py
qleegss/pdf/data_preview.py
qleegss/pdf/msyhbd.ttc
qleegss/pdf/sleep_report.py
qleegss/plot/__init__.py
qleegss/plot/plot_acc.py
qleegss/plot/plot_data_preview.py
qleegss/plot/plot_eeg_spectrogram.py
qleegss/plot/plot_stage.py
qleegss/plot/plot_stage2.py
qleegss/plot/plot_sw.py
qleegss/plot/plot_sw_HF.py
qleegss/test/__init__.py
qleegss/test/load_acc_test.py
qleegss/test/load_ar2_test.py
qleegss/test/load_ar4_test.py
qlsleeps-0.0.36.dist-info/LICENSE
qlsleeps-0.0.36.dist-info/METADATA
qlsleeps-0.0.36.dist-info/WHEEL
qlsleeps-0.0.36.dist-info/top_level.txt
qlsleeps-0.0.36.dist-info/RECORD
